odoo/addons/sale_partner_company_group/README.rst
odoo/addons/sale_partner_company_group/__init__.py
odoo/addons/sale_partner_company_group/__manifest__.py
odoo/addons/sale_partner_company_group/hooks.py
odoo/addons/sale_partner_company_group/i18n/es.po
odoo/addons/sale_partner_company_group/i18n/it.po
odoo/addons/sale_partner_company_group/i18n/pt_BR.po
odoo/addons/sale_partner_company_group/i18n/sale_partner_company_group.pot
odoo/addons/sale_partner_company_group/i18n/zh_CN.po
odoo/addons/sale_partner_company_group/models/__init__.py
odoo/addons/sale_partner_company_group/models/res_partner.py
odoo/addons/sale_partner_company_group/models/sale_order.py
odoo/addons/sale_partner_company_group/readme/CONTRIBUTORS.md
odoo/addons/sale_partner_company_group/readme/CREDITS.md
odoo/addons/sale_partner_company_group/readme/DESCRIPTION.md
odoo/addons/sale_partner_company_group/static/description/icon.png
odoo/addons/sale_partner_company_group/static/description/index.html
odoo/addons/sale_partner_company_group/tests/__init__.py
odoo/addons/sale_partner_company_group/tests/test_sale_partner_company_group.py
odoo/addons/sale_partner_company_group/views/sale_order_view.xml
odoo_addon_sale_partner_company_group-18.0.1.0.0.3.dist-info/METADATA
odoo_addon_sale_partner_company_group-18.0.1.0.0.3.dist-info/WHEEL
odoo_addon_sale_partner_company_group-18.0.1.0.0.3.dist-info/top_level.txt
odoo_addon_sale_partner_company_group-18.0.1.0.0.3.dist-info/RECORD
