Metadata-Version: 2.1
Name: odoo-addon-sale_partner_company_group
Version: 18.0.1.0.0.3
Requires-Python: >=3.10
Requires-Dist: odoo-addon-base_partner_company_group==18.0.*
Requires-Dist: odoo==18.0.*
Summary: Adds the possibility to add a company group to a company
Home-page: https://github.com/OCA/partner-contact
License: AGPL-3
Author: Camptocamp SA, Odoo Community Association (OCA)
Author-email: support@odoo-community.org
Classifier: Programming Language :: Python
Classifier: Framework :: Odoo
Classifier: Framework :: Odoo :: 18.0
Classifier: License :: OSI Approved :: GNU Affero General Public License v3
